{
  "stops": [
    {
      "stop_id": "S08",
      "name": "Icknield Port Rd",
      "deprivation_score": 0.977,
      "imd_rank": 765,
      "imd_decile": 1,
      "lsoa": "E01009143",
      "deprivation_band": "high",
      "fixed_coverage": true,
      "msoa_name": "Five Ways North",
      "notes": "Route 8A/8C; IMD decile 1 (England's most deprived 10%)"
    },
    {
      "stop_id": "S11",
      "name": "Edgbaston Village Metro",
      "deprivation_score": 0.977,
      "imd_rank": 765,
      "imd_decile": 1,
      "lsoa": "E01009143",
      "deprivation_band": "high",
      "fixed_coverage": true,
      "msoa_name": "Five Ways North",
      "notes": "Metro interchange, route 126; shares an LSOA with S08; IMD decile 1"
    },
    {
      "stop_id": "S09",
      "name": "Belgrave Interchange",
      "deprivation_score": 0.975,
      "imd_rank": 830,
      "imd_decile": 1,
      "lsoa": "E01033640",
      "deprivation_band": "high",
      "fixed_coverage": true,
      "msoa_name": "Attwood Green & Park Central",
      "notes": "Route 8A/8C interchange; IMD decile 1"
    },
    {
      "stop_id": "S04",
      "name": "Soho Hill",
      "deprivation_score": 0.974,
      "imd_rank": 871,
      "imd_decile": 1,
      "lsoa": "E01033638",
      "deprivation_band": "high",
      "fixed_coverage": true,
      "msoa_name": "Hockley & Jewellery Quarter",
      "notes": "Northern Ladywood / Handsworth edge; IMD decile 1"
    },
    {
      "stop_id": "S14",
      "name": "Mencap Centre",
      "deprivation_score": 0.958,
      "imd_rank": 1394,
      "imd_decile": 1,
      "lsoa": "E01010062",
      "deprivation_band": "high",
      "fixed_coverage": true,
      "msoa_name": "Sandwell 026",
      "notes": "Only stop outside Birmingham LA (Sandwell); Mencap disability services; IMD decile 1"
    },
    {
      "stop_id": "S05",
      "name": "Five Ways (Metro)",
      "deprivation_score": 0.933,
      "imd_rank": 2197,
      "imd_decile": 1,
      "lsoa": "E01033639",
      "deprivation_band": "medium",
      "fixed_coverage": true,
      "msoa_name": "Five Ways North",
      "notes": "Metro stop; commuter interchange; IMD decile 1 despite affluent-area perception of Edgbaston/Brindleyplace"
    },
    {
      "stop_id": "S12",
      "name": "Summerfield Park",
      "deprivation_score": 0.933,
      "imd_rank": 2203,
      "imd_decile": 1,
      "lsoa": "E01009152",
      "deprivation_band": "medium",
      "fixed_coverage": true,
      "msoa_name": "Summerfield",
      "notes": "Route 80; IMD decile 1"
    },
    {
      "stop_id": "S06",
      "name": "Dudley Rd",
      "deprivation_score": 0.926,
      "imd_rank": 2431,
      "imd_decile": 1,
      "lsoa": "E01009153",
      "deprivation_band": "medium",
      "fixed_coverage": true,
      "msoa_name": "Summerfield",
      "notes": "Route 80; City Hospital corridor; IMD decile 1"
    },
    {
      "stop_id": "S15",
      "name": "Summerfield Crescent",
      "deprivation_score": 0.926,
      "imd_rank": 2431,
      "imd_decile": 1,
      "lsoa": "E01009153",
      "deprivation_band": "medium",
      "fixed_coverage": true,
      "msoa_name": "Summerfield",
      "notes": "Route 80; shares an LSOA with S06; IMD decile 1"
    },
    {
      "stop_id": "S13",
      "name": "City Rd Medical Centre",
      "deprivation_score": 0.884,
      "imd_rank": 3798,
      "imd_decile": 2,
      "lsoa": "E01009346",
      "deprivation_band": "medium",
      "fixed_coverage": true,
      "msoa_name": "Summerfield",
      "notes": "Healthcare-access stop, route 80; IMD decile 2"
    },
    {
      "stop_id": "S10",
      "name": "Ladywood Fire Station",
      "deprivation_score": 0.789,
      "imd_rank": 6930,
      "imd_decile": 3,
      "lsoa": "E01009140",
      "deprivation_band": "low",
      "fixed_coverage": true,
      "msoa_name": "Rotton Park",
      "notes": "Route 80; IMD decile 3"
    },
    {
      "stop_id": "S02",
      "name": "Spring St",
      "deprivation_score": 0.768,
      "imd_rank": 7607,
      "imd_decile": 3,
      "lsoa": "E01033624",
      "deprivation_band": "low",
      "fixed_coverage": true,
      "msoa_name": "Attwood Green & Park Central",
      "notes": "Route 8A/8C; IMD decile 3"
    },
    {
      "stop_id": "S07",
      "name": "Five Ways Station",
      "deprivation_score": 0.718,
      "imd_rank": 9262,
      "imd_decile": 3,
      "lsoa": "E01033626",
      "deprivation_band": "low",
      "fixed_coverage": true,
      "msoa_name": "Attwood Green & Park Central",
      "notes": "Ring Road interchange, multiple routes converge; IMD decile 3"
    },
    {
      "stop_id": "S01",
      "name": "New Street Station",
      "deprivation_score": 0.687,
      "imd_rank": 10295,
      "imd_decile": 4,
      "lsoa": "E01033615",
      "deprivation_band": "low",
      "fixed_coverage": true,
      "msoa_name": "Digbeth",
      "notes": "City-centre rail terminus; IMD decile 4 \u2014 least deprived Ladywood model stop, but still in England's most-deprived 40%"
    },
    {
      "stop_id": "S03",
      "name": "Jewellery Quarter Stn",
      "deprivation_score": 0.573,
      "imd_rank": 14019,
      "imd_decile": 5,
      "lsoa": "E01033559",
      "deprivation_band": "low",
      "fixed_coverage": true,
      "msoa_name": "Hockley & Jewellery Quarter",
      "notes": "Rail + Metro interchange, partially gentrified; IMD decile 5 \u2014 only Ladywood model stop outside the most-deprived 40% of England"
    }
  ],
  "summary": {
    "n_stops": 15,
    "n_high_deprivation_stops": 5,
    "n_high_dep_unserved_by_fixed": 0,
    "high_dep_unserved_names": [],
    "allocation_mismatch_fixed": 0.348,
    "allocation_mismatch_dynamic": 0.344,
    "mismatch_snapshots_compared": 32
  },
  "national_context": {
    "n_stops_imd_decile_1": 9,
    "n_stops_imd_decile_1_to_3": 13,
    "note": "9/15 Ladywood model stops are in IMD 2019 decile 1 (England's most deprived 10% of LSOAs); 13/15 are in deciles 1-3 (most-deprived 30%). Only S01 (decile 4) and S03 (decile 5) fall outside the most-deprived 40%."
  },
  "data_source": "MHCLG English Indices of Deprivation 2019 (IMD 2019), LSOA level",
  "methodology": "imd_rank and imd_decile are the England-wide IMD 2019 values for each stop's LSOA (data/imd/ladywood_imd_2019.json, live MHCLG fetch). deprivation_score = 1 - (imd_rank - 1) / 32843, for display ordering only. deprivation_band is a corridor-relative tertile over imd_rank (assign_deprivation_bands); see national_context for the absolute (decile-based) headline figure. Allocation-mismatch index = sum(|service share - demand share|) / 2 across stops (the standard dissimilarity index, 0 = perfectly proportional, 1 = total mismatch), averaged across every scenario and time window in the live route plan \u2014 i.e. how closely bus allocation tracks demand as it shifts with weather and time of day."
}